{"variants":[{"traits":[{"interfaceLanguage":"swift"}],"paths":["\/documentation\/charcoal"]}],"sections":[],"hierarchy":{"paths":[[]]},"kind":"symbol","schemaVersion":{"minor":3,"patch":0,"major":0},"topicSections":[{"identifiers":["doc:\/\/charcoal-ios.Charcoal\/documentation\/Charcoal\/Balloons","doc:\/\/charcoal-ios.Charcoal\/documentation\/Charcoal\/Buttons","doc:\/\/charcoal-ios.Charcoal\/documentation\/Charcoal\/Hints","doc:\/\/charcoal-ios.Charcoal\/documentation\/Charcoal\/Modals","doc:\/\/charcoal-ios.Charcoal\/documentation\/Charcoal\/Spinners","doc:\/\/charcoal-ios.Charcoal\/documentation\/Charcoal\/Switch","doc:\/\/charcoal-ios.Charcoal\/documentation\/Charcoal\/Textfields","doc:\/\/charcoal-ios.Charcoal\/documentation\/Charcoal\/Toasts","doc:\/\/charcoal-ios.Charcoal\/documentation\/Charcoal\/Tooltips","doc:\/\/charcoal-ios.Charcoal\/documentation\/Charcoal\/Typographies","doc:\/\/charcoal-ios.Charcoal\/documentation\/Charcoal\/DynamicType"],"generated":true,"anchor":"Articles","title":"Articles"},{"identifiers":["doc:\/\/charcoal-ios.Charcoal\/documentation\/Charcoal\/CharcoalBalloon","doc:\/\/charcoal-ios.Charcoal\/documentation\/Charcoal\/CharcoalDefaultMButton","doc:\/\/charcoal-ios.Charcoal\/documentation\/Charcoal\/CharcoalDefaultOverlayMButton","doc:\/\/charcoal-ios.Charcoal\/documentation\/Charcoal\/CharcoalDefaultOverlaySButton","doc:\/\/charcoal-ios.Charcoal\/documentation\/Charcoal\/CharcoalDefaultSButton","doc:\/\/charcoal-ios.Charcoal\/documentation\/Charcoal\/CharcoalHintView","doc:\/\/charcoal-ios.Charcoal\/documentation\/Charcoal\/CharcoalIdentifiableOverlayView","doc:\/\/charcoal-ios.Charcoal\/documentation\/Charcoal\/CharcoalLinkButton","doc:\/\/charcoal-ios.Charcoal\/documentation\/Charcoal\/CharcoalNavigationMButton","doc:\/\/charcoal-ios.Charcoal\/documentation\/Charcoal\/CharcoalNavigationSButton","doc:\/\/charcoal-ios.Charcoal\/documentation\/Charcoal\/CharcoalPrimaryMButton","doc:\/\/charcoal-ios.Charcoal\/documentation\/Charcoal\/CharcoalPrimarySButton","doc:\/\/charcoal-ios.Charcoal\/documentation\/Charcoal\/CharcoalSnackBar","doc:\/\/charcoal-ios.Charcoal\/documentation\/Charcoal\/CharcoalSpinner-swift.class","doc:\/\/charcoal-ios.Charcoal\/documentation\/Charcoal\/CharcoalSwitch","doc:\/\/charcoal-ios.Charcoal\/documentation\/Charcoal\/CharcoalSwitchingButton","doc:\/\/charcoal-ios.Charcoal\/documentation\/Charcoal\/CharcoalTextField","doc:\/\/charcoal-ios.Charcoal\/documentation\/Charcoal\/CharcoalTextFieldView","doc:\/\/charcoal-ios.Charcoal\/documentation\/Charcoal\/CharcoalToast","doc:\/\/charcoal-ios.Charcoal\/documentation\/Charcoal\/CharcoalTooltip","doc:\/\/charcoal-ios.Charcoal\/documentation\/Charcoal\/CharcoalTypography10","doc:\/\/charcoal-ios.Charcoal\/documentation\/Charcoal\/CharcoalTypography12","doc:\/\/charcoal-ios.Charcoal\/documentation\/Charcoal\/CharcoalTypography14","doc:\/\/charcoal-ios.Charcoal\/documentation\/Charcoal\/CharcoalTypography16","doc:\/\/charcoal-ios.Charcoal\/documentation\/Charcoal\/CharcoalTypography20","doc:\/\/charcoal-ios.Charcoal\/documentation\/Charcoal\/CharcoalTypographyLabel","doc:\/\/charcoal-ios.Charcoal\/documentation\/Charcoal\/ColorAsset"],"generated":true,"title":"Classes","anchor":"Classes"},{"title":"Protocols","generated":true,"anchor":"Protocols","identifiers":["doc:\/\/charcoal-ios.Charcoal\/documentation\/Charcoal\/CharcoalButton","doc:\/\/charcoal-ios.Charcoal\/documentation\/Charcoal\/CharcoalButtonModifier","doc:\/\/charcoal-ios.Charcoal\/documentation\/Charcoal\/CharcoalTextFieldViewDelegate"]},{"generated":true,"anchor":"Structures","identifiers":["doc:\/\/charcoal-ios.Charcoal\/documentation\/Charcoal\/CharcoalAction","doc:\/\/charcoal-ios.Charcoal\/documentation\/Charcoal\/CharcoalBorderRadius","doc:\/\/charcoal-ios.Charcoal\/documentation\/Charcoal\/CharcoalConfig","doc:\/\/charcoal-ios.Charcoal\/documentation\/Charcoal\/CharcoalFoundation-swift.struct","doc:\/\/charcoal-ios.Charcoal\/documentation\/Charcoal\/CharcoalHint","doc:\/\/charcoal-ios.Charcoal\/documentation\/Charcoal\/CharcoalSize","doc:\/\/charcoal-ios.Charcoal\/documentation\/Charcoal\/CharcoalSpacing","doc:\/\/charcoal-ios.Charcoal\/documentation\/Charcoal\/CharcoalSpinner-swift.struct","doc:\/\/charcoal-ios.Charcoal\/documentation\/Charcoal\/CharcoalSpinnerModifier","doc:\/\/charcoal-ios.Charcoal\/documentation\/Charcoal\/CharcoalThe12","doc:\/\/charcoal-ios.Charcoal\/documentation\/Charcoal\/CharcoalToastAnimationConfiguration","doc:\/\/charcoal-ios.Charcoal\/documentation\/Charcoal\/CharcoalTypography","doc:\/\/charcoal-ios.Charcoal\/documentation\/Charcoal\/ImageAsset","doc:\/\/charcoal-ios.Charcoal\/documentation\/Charcoal\/LayoutPriority"],"title":"Structures"},{"title":"Variables","anchor":"Variables","generated":true,"identifiers":["doc:\/\/charcoal-ios.Charcoal\/documentation\/Charcoal\/charcoalFoundation-swift.var"]},{"anchor":"Type-Aliases","title":"Type Aliases","generated":true,"identifiers":["doc:\/\/charcoal-ios.Charcoal\/documentation\/Charcoal\/ActionCallback","doc:\/\/charcoal-ios.Charcoal\/documentation\/Charcoal\/AssetColorTypeAlias","doc:\/\/charcoal-ios.Charcoal\/documentation\/Charcoal\/AssetImageTypeAlias"]},{"title":"Enumerations","generated":true,"anchor":"Enumerations","identifiers":["doc:\/\/charcoal-ios.Charcoal\/documentation\/Charcoal\/CharcoalAsset","doc:\/\/charcoal-ios.Charcoal\/documentation\/Charcoal\/CharcoalButtonSize","doc:\/\/charcoal-ios.Charcoal\/documentation\/Charcoal\/CharcoalButtonStyle","doc:\/\/charcoal-ios.Charcoal\/documentation\/Charcoal\/CharcoalModalStyle","doc:\/\/charcoal-ios.Charcoal\/documentation\/Charcoal\/CharcoalOverlayInteractionMode","doc:\/\/charcoal-ios.Charcoal\/documentation\/Charcoal\/CharcoalPopupViewEdge","doc:\/\/charcoal-ios.Charcoal\/documentation\/Charcoal\/CharcoalToastAppearance","doc:\/\/charcoal-ios.Charcoal\/documentation\/Charcoal\/CharcoalTooltipLayoutPriority"]},{"generated":true,"anchor":"Extended-Modules","title":"Extended Modules","identifiers":["doc:\/\/charcoal-ios.Charcoal\/documentation\/Charcoal\/CoreFoundation","doc:\/\/charcoal-ios.Charcoal\/documentation\/Charcoal\/SwiftUICore","doc:\/\/charcoal-ios.Charcoal\/documentation\/Charcoal\/UIKit"]}],"primaryContentSections":[{"kind":"content","content":[{"anchor":"Featured","text":"Featured","type":"heading","level":3},{"type":"links","style":"detailedGrid","items":["doc:\/\/charcoal-ios.Charcoal\/documentation\/Charcoal\/Typographies","doc:\/\/charcoal-ios.Charcoal\/documentation\/Charcoal\/Buttons","doc:\/\/charcoal-ios.Charcoal\/documentation\/Charcoal\/Tooltips","doc:\/\/charcoal-ios.Charcoal\/documentation\/Charcoal\/Spinners","doc:\/\/charcoal-ios.Charcoal\/documentation\/Charcoal\/Toasts","doc:\/\/charcoal-ios.Charcoal\/documentation\/Charcoal\/Balloons","doc:\/\/charcoal-ios.Charcoal\/documentation\/Charcoal\/Textfields","doc:\/\/charcoal-ios.Charcoal\/documentation\/Charcoal\/Modals","doc:\/\/charcoal-ios.Charcoal\/documentation\/Charcoal\/Hints","doc:\/\/charcoal-ios.Charcoal\/documentation\/Charcoal\/Switch"]},{"anchor":"Installation","level":3,"text":"Installation","type":"heading"},{"inlineContent":[{"text":"Swift Package Managerを使ってライブラリをインストールすることができます。","type":"text"}],"type":"paragraph"},{"type":"codeListing","syntax":"swift","code":["dependencies: [","  .package(url: \"https:\/\/github.com\/pixiv\/charcoal-ios\", .upToNextMajor(from: \"1.0.0\"))","]"]}]}],"abstract":[{"text":"PIXIV Design System","type":"text"}],"identifier":{"url":"doc:\/\/charcoal-ios.Charcoal\/documentation\/Charcoal","interfaceLanguage":"swift"},"metadata":{"images":[{"identifier":"charcoal-icon.png","type":"icon"}],"symbolKind":"module","title":"Charcoal","externalID":"Charcoal","roleHeading":"Framework","role":"collection","modules":[{"name":"Charcoal"}]},"references":{"doc://charcoal-ios.Charcoal/documentation/Charcoal/ImageAsset":{"title":"ImageAsset","fragments":[{"text":"struct","kind":"keyword"},{"kind":"text","text":" "},{"text":"ImageAsset","kind":"identifier"}],"role":"symbol","abstract":[],"identifier":"doc:\/\/charcoal-ios.Charcoal\/documentation\/Charcoal\/ImageAsset","type":"topic","navigatorTitle":[{"text":"ImageAsset","kind":"identifier"}],"kind":"symbol","url":"\/documentation\/charcoal\/imageasset"},"doc://charcoal-ios.Charcoal/documentation/Charcoal/CharcoalAction":{"title":"CharcoalAction","url":"\/documentation\/charcoal\/charcoalaction","identifier":"doc:\/\/charcoal-ios.Charcoal\/documentation\/Charcoal\/CharcoalAction","type":"topic","kind":"symbol","role":"symbol","fragments":[{"text":"struct","kind":"keyword"},{"text":" ","kind":"text"},{"text":"CharcoalAction","kind":"identifier"}],"navigatorTitle":[{"kind":"identifier","text":"CharcoalAction"}],"abstract":[]},"doc://charcoal-ios.Charcoal/documentation/Charcoal/CharcoalHintView":{"url":"\/documentation\/charcoal\/charcoalhintview","kind":"symbol","type":"topic","role":"symbol","fragments":[{"text":"class","kind":"keyword"},{"text":" ","kind":"text"},{"text":"CharcoalHintView","kind":"identifier"}],"title":"CharcoalHintView","identifier":"doc:\/\/charcoal-ios.Charcoal\/documentation\/Charcoal\/CharcoalHintView","navigatorTitle":[{"kind":"identifier","text":"CharcoalHintView"}],"abstract":[]},"doc://charcoal-ios.Charcoal/documentation/Charcoal/CharcoalIdentifiableOverlayView":{"navigatorTitle":[{"text":"CharcoalIdentifiableOverlayView","kind":"identifier"}],"url":"\/documentation\/charcoal\/charcoalidentifiableoverlayview","title":"CharcoalIdentifiableOverlayView","kind":"symbol","role":"symbol","identifier":"doc:\/\/charcoal-ios.Charcoal\/documentation\/Charcoal\/CharcoalIdentifiableOverlayView","abstract":[],"fragments":[{"kind":"keyword","text":"class"},{"kind":"text","text":" "},{"text":"CharcoalIdentifiableOverlayView","kind":"identifier"}],"type":"topic"},"doc://charcoal-ios.Charcoal/documentation/Charcoal/CharcoalButtonSize":{"role":"symbol","kind":"symbol","identifier":"doc:\/\/charcoal-ios.Charcoal\/documentation\/Charcoal\/CharcoalButtonSize","type":"topic","abstract":[],"fragments":[{"text":"enum","kind":"keyword"},{"text":" ","kind":"text"},{"text":"CharcoalButtonSize","kind":"identifier"}],"url":"\/documentation\/charcoal\/charcoalbuttonsize","title":"CharcoalButtonSize","navigatorTitle":[{"text":"CharcoalButtonSize","kind":"identifier"}]},"doc://charcoal-ios.Charcoal/documentation/Charcoal/CharcoalSpinner-swift.class":{"type":"topic","role":"symbol","fragments":[{"kind":"keyword","text":"class"},{"kind":"text","text":" "},{"text":"CharcoalSpinner","kind":"identifier"}],"navigatorTitle":[{"kind":"identifier","text":"CharcoalSpinner"}],"identifier":"doc:\/\/charcoal-ios.Charcoal\/documentation\/Charcoal\/CharcoalSpinner-swift.class","url":"\/documentation\/charcoal\/charcoalspinner-swift.class","abstract":[{"type":"text","text":"Displays a spinner on the screen."}],"kind":"symbol","title":"CharcoalSpinner"},"doc://charcoal-ios.Charcoal/documentation/Charcoal/CharcoalTooltip":{"title":"CharcoalTooltip","abstract":[],"identifier":"doc:\/\/charcoal-ios.Charcoal\/documentation\/Charcoal\/CharcoalTooltip","type":"topic","navigatorTitle":[{"kind":"identifier","text":"CharcoalTooltip"}],"role":"symbol","url":"\/documentation\/charcoal\/charcoaltooltip","kind":"symbol","fragments":[{"kind":"keyword","text":"class"},{"text":" ","kind":"text"},{"text":"CharcoalTooltip","kind":"identifier"}]},"doc://charcoal-ios.Charcoal/documentation/Charcoal/Toasts":{"images":[{"type":"card","identifier":"Toasts.png"}],"url":"\/documentation\/charcoal\/toasts","identifier":"doc:\/\/charcoal-ios.Charcoal\/documentation\/Charcoal\/Toasts","kind":"article","type":"topic","title":"Charocal Toasts","abstract":[{"text":"Charcoal Toasts can be used to display a message and Snackbar to the user.","type":"text"}],"role":"collectionGroup"},"doc://charcoal-ios.Charcoal/documentation/Charcoal/CharcoalHint":{"kind":"symbol","abstract":[],"title":"CharcoalHint","navigatorTitle":[{"text":"CharcoalHint","kind":"identifier"}],"type":"topic","role":"symbol","fragments":[{"kind":"keyword","text":"struct"},{"kind":"text","text":" "},{"kind":"identifier","text":"CharcoalHint"}],"identifier":"doc:\/\/charcoal-ios.Charcoal\/documentation\/Charcoal\/CharcoalHint","url":"\/documentation\/charcoal\/charcoalhint"},"doc://charcoal-ios.Charcoal/documentation/Charcoal/AssetImageTypeAlias":{"kind":"symbol","type":"topic","url":"\/documentation\/charcoal\/assetimagetypealias","abstract":[],"identifier":"doc:\/\/charcoal-ios.Charcoal\/documentation\/Charcoal\/AssetImageTypeAlias","title":"AssetImageTypeAlias","navigatorTitle":[{"kind":"identifier","text":"AssetImageTypeAlias"}],"deprecated":true,"role":"symbol","fragments":[{"text":"typealias","kind":"keyword"},{"kind":"text","text":" "},{"kind":"identifier","text":"AssetImageTypeAlias"}]},"Tooltips.png":{"identifier":"Tooltips.png","variants":[{"traits":["2x","light"],"url":"\/images\/charcoal-ios.Charcoal\/Tooltips@2x.png"},{"traits":["2x","dark"],"url":"\/images\/charcoal-ios.Charcoal\/Tooltips~dark@2x.png"}],"type":"image","alt":"Charcoal Tooltips can be used to provide additional information about an element when the user click on it."},"doc://charcoal-ios.Charcoal/documentation/Charcoal/Modals":{"kind":"article","images":[{"type":"card","identifier":"Modals.png"}],"type":"topic","url":"\/documentation\/charcoal\/modals","abstract":[{"text":"Charcoal Modals are designed to show a message in a modal container.","type":"text"}],"identifier":"doc:\/\/charcoal-ios.Charcoal\/documentation\/Charcoal\/Modals","title":"Charocal Modals","role":"collectionGroup"},"doc://charcoal-ios.Charcoal/documentation/Charcoal/Textfields":{"images":[{"type":"card","identifier":"TextFields.png"}],"url":"\/documentation\/charcoal\/textfields","identifier":"doc:\/\/charcoal-ios.Charcoal\/documentation\/Charcoal\/Textfields","kind":"article","type":"topic","title":"Charocal TextFields","abstract":[{"text":"Charcoal Textfields are designed to be used in a variety of contexts and are highly customizable.","type":"text"}],"role":"collectionGroup"},"doc://charcoal-ios.Charcoal/documentation/Charcoal/CoreFoundation":{"kind":"symbol","role":"collection","type":"topic","abstract":[],"title":"CoreFoundation","identifier":"doc:\/\/charcoal-ios.Charcoal\/documentation\/Charcoal\/CoreFoundation","url":"\/documentation\/charcoal\/corefoundation"},"doc://charcoal-ios.Charcoal/documentation/Charcoal/AssetColorTypeAlias":{"kind":"symbol","type":"topic","url":"\/documentation\/charcoal\/assetcolortypealias","abstract":[],"identifier":"doc:\/\/charcoal-ios.Charcoal\/documentation\/Charcoal\/AssetColorTypeAlias","title":"AssetColorTypeAlias","navigatorTitle":[{"kind":"identifier","text":"AssetColorTypeAlias"}],"deprecated":true,"role":"symbol","fragments":[{"text":"typealias","kind":"keyword"},{"kind":"text","text":" "},{"kind":"identifier","text":"AssetColorTypeAlias"}]},"doc://charcoal-ios.Charcoal/documentation/Charcoal/CharcoalTypography":{"abstract":[],"type":"topic","fragments":[{"kind":"keyword","text":"struct"},{"text":" ","kind":"text"},{"text":"CharcoalTypography","kind":"identifier"}],"title":"CharcoalTypography","url":"\/documentation\/charcoal\/charcoaltypography","kind":"symbol","navigatorTitle":[{"text":"CharcoalTypography","kind":"identifier"}],"role":"symbol","identifier":"doc:\/\/charcoal-ios.Charcoal\/documentation\/Charcoal\/CharcoalTypography"},"doc://charcoal-ios.Charcoal/documentation/Charcoal/CharcoalTypography12":{"fragments":[{"kind":"keyword","text":"class"},{"kind":"text","text":" "},{"text":"CharcoalTypography12","kind":"identifier"}],"navigatorTitle":[{"text":"CharcoalTypography12","kind":"identifier"}],"url":"\/documentation\/charcoal\/charcoaltypography12","role":"symbol","title":"CharcoalTypography12","identifier":"doc:\/\/charcoal-ios.Charcoal\/documentation\/Charcoal\/CharcoalTypography12","abstract":[],"kind":"symbol","type":"topic"},"doc://charcoal-ios.Charcoal/documentation/Charcoal/CharcoalTypography14":{"kind":"symbol","identifier":"doc:\/\/charcoal-ios.Charcoal\/documentation\/Charcoal\/CharcoalTypography14","title":"CharcoalTypography14","abstract":[],"navigatorTitle":[{"kind":"identifier","text":"CharcoalTypography14"}],"role":"symbol","url":"\/documentation\/charcoal\/charcoaltypography14","type":"topic","fragments":[{"text":"class","kind":"keyword"},{"kind":"text","text":" "},{"kind":"identifier","text":"CharcoalTypography14"}]},"doc://charcoal-ios.Charcoal/documentation/Charcoal/CharcoalSwitch":{"role":"symbol","abstract":[],"url":"\/documentation\/charcoal\/charcoalswitch","fragments":[{"kind":"keyword","text":"class"},{"text":" ","kind":"text"},{"text":"CharcoalSwitch","kind":"identifier"}],"kind":"symbol","title":"CharcoalSwitch","navigatorTitle":[{"text":"CharcoalSwitch","kind":"identifier"}],"type":"topic","identifier":"doc:\/\/charcoal-ios.Charcoal\/documentation\/Charcoal\/CharcoalSwitch"},"doc://charcoal-ios.Charcoal/documentation/Charcoal/LayoutPriority":{"abstract":[],"kind":"symbol","title":"LayoutPriority","role":"symbol","navigatorTitle":[{"text":"LayoutPriority","kind":"identifier"}],"identifier":"doc:\/\/charcoal-ios.Charcoal\/documentation\/Charcoal\/LayoutPriority","type":"topic","url":"\/documentation\/charcoal\/layoutpriority","fragments":[{"text":"struct","kind":"keyword"},{"kind":"text","text":" "},{"text":"LayoutPriority","kind":"identifier"}]},"doc://charcoal-ios.Charcoal/documentation/Charcoal/CharcoalPopupViewEdge":{"role":"symbol","type":"topic","identifier":"doc:\/\/charcoal-ios.Charcoal\/documentation\/Charcoal\/CharcoalPopupViewEdge","url":"\/documentation\/charcoal\/charcoalpopupviewedge","fragments":[{"text":"enum","kind":"keyword"},{"kind":"text","text":" "},{"text":"CharcoalPopupViewEdge","kind":"identifier"}],"abstract":[],"navigatorTitle":[{"kind":"identifier","text":"CharcoalPopupViewEdge"}],"kind":"symbol","title":"CharcoalPopupViewEdge"},"doc://charcoal-ios.Charcoal/documentation/Charcoal/CharcoalDefaultSButton":{"role":"symbol","navigatorTitle":[{"kind":"identifier","text":"CharcoalDefaultSButton"}],"url":"\/documentation\/charcoal\/charcoaldefaultsbutton","kind":"symbol","type":"topic","title":"CharcoalDefaultSButton","identifier":"doc:\/\/charcoal-ios.Charcoal\/documentation\/Charcoal\/CharcoalDefaultSButton","abstract":[],"fragments":[{"kind":"keyword","text":"class"},{"text":" ","kind":"text"},{"kind":"identifier","text":"CharcoalDefaultSButton"}]},"doc://charcoal-ios.Charcoal/documentation/Charcoal/CharcoalDefaultOverlaySButton":{"url":"\/documentation\/charcoal\/charcoaldefaultoverlaysbutton","fragments":[{"text":"class","kind":"keyword"},{"text":" ","kind":"text"},{"kind":"identifier","text":"CharcoalDefaultOverlaySButton"}],"identifier":"doc:\/\/charcoal-ios.Charcoal\/documentation\/Charcoal\/CharcoalDefaultOverlaySButton","navigatorTitle":[{"text":"CharcoalDefaultOverlaySButton","kind":"identifier"}],"kind":"symbol","type":"topic","abstract":[],"title":"CharcoalDefaultOverlaySButton","role":"symbol"},"Balloon.png":{"identifier":"Balloon.png","variants":[{"traits":["2x","light"],"url":"\/images\/charcoal-ios.Charcoal\/Balloon@2x.png"},{"traits":["2x","dark"],"url":"\/images\/charcoal-ios.Charcoal\/Balloon~dark@2x.png"}],"type":"image","alt":"Charcoal Balloons are designed to show a message in a balloon-shaped container."},"doc://charcoal-ios.Charcoal/documentation/Charcoal/UIKit":{"identifier":"doc:\/\/charcoal-ios.Charcoal\/documentation\/Charcoal\/UIKit","title":"UIKit","kind":"symbol","url":"\/documentation\/charcoal\/uikit","role":"collection","type":"topic","abstract":[]},"doc://charcoal-ios.Charcoal/documentation/Charcoal/CharcoalPrimaryMButton":{"navigatorTitle":[{"kind":"identifier","text":"CharcoalPrimaryMButton"}],"title":"CharcoalPrimaryMButton","url":"\/documentation\/charcoal\/charcoalprimarymbutton","type":"topic","identifier":"doc:\/\/charcoal-ios.Charcoal\/documentation\/Charcoal\/CharcoalPrimaryMButton","kind":"symbol","abstract":[],"role":"symbol","fragments":[{"kind":"keyword","text":"class"},{"text":" ","kind":"text"},{"kind":"identifier","text":"CharcoalPrimaryMButton"}]},"doc://charcoal-ios.Charcoal/documentation/Charcoal/CharcoalTextFieldViewDelegate":{"kind":"symbol","navigatorTitle":[{"kind":"identifier","text":"CharcoalTextFieldViewDelegate"}],"abstract":[],"title":"CharcoalTextFieldViewDelegate","type":"topic","role":"symbol","identifier":"doc:\/\/charcoal-ios.Charcoal\/documentation\/Charcoal\/CharcoalTextFieldViewDelegate","fragments":[{"text":"protocol","kind":"keyword"},{"text":" ","kind":"text"},{"text":"CharcoalTextFieldViewDelegate","kind":"identifier"}],"url":"\/documentation\/charcoal\/charcoaltextfieldviewdelegate"},"doc://charcoal-ios.Charcoal/documentation/Charcoal/Hints":{"kind":"article","images":[{"type":"card","identifier":"Hints.png"}],"type":"topic","url":"\/documentation\/charcoal\/hints","abstract":[{"text":"Charcoal Hints are designed to display in page hints and tips to the user.","type":"text"}],"identifier":"doc:\/\/charcoal-ios.Charcoal\/documentation\/Charcoal\/Hints","title":"Charocal Hints","role":"collectionGroup"},"doc://charcoal-ios.Charcoal/documentation/Charcoal/ActionCallback":{"navigatorTitle":[{"kind":"identifier","text":"ActionCallback"}],"url":"\/documentation\/charcoal\/actioncallback","title":"ActionCallback","kind":"symbol","role":"symbol","identifier":"doc:\/\/charcoal-ios.Charcoal\/documentation\/Charcoal\/ActionCallback","abstract":[],"fragments":[{"kind":"keyword","text":"typealias"},{"text":" ","kind":"text"},{"text":"ActionCallback","kind":"identifier"}],"type":"topic"},"doc://charcoal-ios.Charcoal/documentation/Charcoal/CharcoalModalStyle":{"title":"CharcoalModalStyle","abstract":[],"kind":"symbol","role":"symbol","navigatorTitle":[{"kind":"identifier","text":"CharcoalModalStyle"}],"identifier":"doc:\/\/charcoal-ios.Charcoal\/documentation\/Charcoal\/CharcoalModalStyle","type":"topic","url":"\/documentation\/charcoal\/charcoalmodalstyle","fragments":[{"text":"enum","kind":"keyword"},{"text":" ","kind":"text"},{"text":"CharcoalModalStyle","kind":"identifier"}]},"Modals.png":{"identifier":"Modals.png","variants":[{"traits":["2x","light"],"url":"\/images\/charcoal-ios.Charcoal\/Modals@2x.png"},{"url":"\/images\/charcoal-ios.Charcoal\/Modals~dark@2x.png","traits":["2x","dark"]}],"type":"image","alt":"Charcoal Modals are designed to show a message in a modal container."},"Switch.png":{"variants":[{"traits":["2x","light"],"url":"\/images\/charcoal-ios.Charcoal\/Switch@2x.png"},{"traits":["2x","dark"],"url":"\/images\/charcoal-ios.Charcoal\/Switch~dark@2x.png"}],"identifier":"Switch.png","type":"image","alt":"Charcoal Switches are designed to allow the user to toggle between two states."},"charcoal-icon.png":{"identifier":"charcoal-icon.png","variants":[{"traits":["1x","light"],"url":"\/images\/charcoal-ios.Charcoal\/charcoal-icon.png"},{"url":"\/images\/charcoal-ios.Charcoal\/charcoal-icon~dark.png","traits":["1x","dark"]}],"type":"image","alt":"A technology icon representing the Charcoal framework."},"doc://charcoal-ios.Charcoal/documentation/Charcoal/CharcoalNavigationSButton":{"title":"CharcoalNavigationSButton","abstract":[],"type":"topic","identifier":"doc:\/\/charcoal-ios.Charcoal\/documentation\/Charcoal\/CharcoalNavigationSButton","kind":"symbol","fragments":[{"kind":"keyword","text":"class"},{"text":" ","kind":"text"},{"kind":"identifier","text":"CharcoalNavigationSButton"}],"role":"symbol","url":"\/documentation\/charcoal\/charcoalnavigationsbutton","navigatorTitle":[{"text":"CharcoalNavigationSButton","kind":"identifier"}]},"doc://charcoal-ios.Charcoal/documentation/Charcoal/CharcoalTextFieldView":{"title":"CharcoalTextFieldView","abstract":[],"role":"symbol","fragments":[{"kind":"keyword","text":"class"},{"kind":"text","text":" "},{"kind":"identifier","text":"CharcoalTextFieldView"}],"kind":"symbol","url":"\/documentation\/charcoal\/charcoaltextfieldview","type":"topic","identifier":"doc:\/\/charcoal-ios.Charcoal\/documentation\/Charcoal\/CharcoalTextFieldView","navigatorTitle":[{"kind":"identifier","text":"CharcoalTextFieldView"}]},"doc://charcoal-ios.Charcoal/documentation/Charcoal/CharcoalTextField":{"title":"CharcoalTextField","identifier":"doc:\/\/charcoal-ios.Charcoal\/documentation\/Charcoal\/CharcoalTextField","kind":"symbol","type":"topic","abstract":[],"navigatorTitle":[{"kind":"identifier","text":"CharcoalTextField"}],"url":"\/documentation\/charcoal\/charcoaltextfield","fragments":[{"kind":"keyword","text":"class"},{"kind":"text","text":" "},{"kind":"identifier","text":"CharcoalTextField"}],"role":"symbol"},"Hints.png":{"variants":[{"traits":["2x","light"],"url":"\/images\/charcoal-ios.Charcoal\/Hints@2x.png"},{"traits":["2x","dark"],"url":"\/images\/charcoal-ios.Charcoal\/Hints~dark@2x.png"}],"identifier":"Hints.png","type":"image","alt":"Charcoal Hints are designed to display in page hints and tips to the user."},"doc://charcoal-ios.Charcoal/documentation/Charcoal/Spinners":{"images":[{"type":"card","identifier":"Spinners.png"}],"url":"\/documentation\/charcoal\/spinners","identifier":"doc:\/\/charcoal-ios.Charcoal\/documentation\/Charcoal\/Spinners","kind":"article","type":"topic","title":"Charocal Spinners","abstract":[{"text":"Charcoal Spinners are designed to display a loading state.","type":"text"}],"role":"collectionGroup"},"doc://charcoal-ios.Charcoal/documentation/Charcoal/CharcoalSpinnerModifier":{"kind":"symbol","type":"topic","role":"symbol","abstract":[],"navigatorTitle":[{"text":"CharcoalSpinnerModifier","kind":"identifier"}],"fragments":[{"kind":"keyword","text":"struct"},{"kind":"text","text":" "},{"text":"CharcoalSpinnerModifier","kind":"identifier"}],"identifier":"doc:\/\/charcoal-ios.Charcoal\/documentation\/Charcoal\/CharcoalSpinnerModifier","url":"\/documentation\/charcoal\/charcoalspinnermodifier","title":"CharcoalSpinnerModifier"},"doc://charcoal-ios.Charcoal/documentation/Charcoal/CharcoalTypography16":{"abstract":[],"title":"CharcoalTypography16","type":"topic","role":"symbol","fragments":[{"text":"class","kind":"keyword"},{"text":" ","kind":"text"},{"kind":"identifier","text":"CharcoalTypography16"}],"identifier":"doc:\/\/charcoal-ios.Charcoal\/documentation\/Charcoal\/CharcoalTypography16","url":"\/documentation\/charcoal\/charcoaltypography16","navigatorTitle":[{"kind":"identifier","text":"CharcoalTypography16"}],"kind":"symbol"},"doc://charcoal-ios.Charcoal/documentation/Charcoal/CharcoalToastAppearance":{"fragments":[{"kind":"keyword","text":"enum"},{"kind":"text","text":" "},{"text":"CharcoalToastAppearance","kind":"identifier"}],"url":"\/documentation\/charcoal\/charcoaltoastappearance","navigatorTitle":[{"text":"CharcoalToastAppearance","kind":"identifier"}],"title":"CharcoalToastAppearance","type":"topic","abstract":[],"role":"symbol","identifier":"doc:\/\/charcoal-ios.Charcoal\/documentation\/Charcoal\/CharcoalToastAppearance","kind":"symbol"},"Typographies.png":{"variants":[{"traits":["2x","light"],"url":"\/images\/charcoal-ios.Charcoal\/Typographies@2x.png"},{"url":"\/images\/charcoal-ios.Charcoal\/Typographies~dark@2x.png","traits":["2x","dark"]}],"identifier":"Typographies.png","type":"image","alt":"Charcoal Typographies are designed to be used in a variety of contexts and are highly customizable."},"doc://charcoal-ios.Charcoal/documentation/Charcoal/CharcoalTooltipLayoutPriority":{"kind":"symbol","type":"topic","abstract":[],"role":"symbol","fragments":[{"text":"enum","kind":"keyword"},{"text":" ","kind":"text"},{"kind":"identifier","text":"CharcoalTooltipLayoutPriority"}],"title":"CharcoalTooltipLayoutPriority","navigatorTitle":[{"kind":"identifier","text":"CharcoalTooltipLayoutPriority"}],"url":"\/documentation\/charcoal\/charcoaltooltiplayoutpriority","identifier":"doc:\/\/charcoal-ios.Charcoal\/documentation\/Charcoal\/CharcoalTooltipLayoutPriority"},"doc://charcoal-ios.Charcoal/documentation/Charcoal/SwiftUICore":{"abstract":[],"identifier":"doc:\/\/charcoal-ios.Charcoal\/documentation\/Charcoal\/SwiftUICore","role":"collection","type":"topic","url":"\/documentation\/charcoal\/swiftuicore","kind":"symbol","title":"SwiftUICore"},"doc://charcoal-ios.Charcoal/documentation/Charcoal/CharcoalDefaultOverlayMButton":{"fragments":[{"text":"class","kind":"keyword"},{"text":" ","kind":"text"},{"text":"CharcoalDefaultOverlayMButton","kind":"identifier"}],"identifier":"doc:\/\/charcoal-ios.Charcoal\/documentation\/Charcoal\/CharcoalDefaultOverlayMButton","title":"CharcoalDefaultOverlayMButton","abstract":[],"url":"\/documentation\/charcoal\/charcoaldefaultoverlaymbutton","role":"symbol","type":"topic","navigatorTitle":[{"text":"CharcoalDefaultOverlayMButton","kind":"identifier"}],"kind":"symbol"},"doc://charcoal-ios.Charcoal/documentation/Charcoal/CharcoalNavigationMButton":{"kind":"symbol","url":"\/documentation\/charcoal\/charcoalnavigationmbutton","fragments":[{"kind":"keyword","text":"class"},{"kind":"text","text":" "},{"text":"CharcoalNavigationMButton","kind":"identifier"}],"abstract":[],"type":"topic","title":"CharcoalNavigationMButton","navigatorTitle":[{"text":"CharcoalNavigationMButton","kind":"identifier"}],"identifier":"doc:\/\/charcoal-ios.Charcoal\/documentation\/Charcoal\/CharcoalNavigationMButton","role":"symbol"},"doc://charcoal-ios.Charcoal/documentation/Charcoal/CharcoalSize":{"identifier":"doc:\/\/charcoal-ios.Charcoal\/documentation\/Charcoal\/CharcoalSize","kind":"symbol","url":"\/documentation\/charcoal\/charcoalsize","abstract":[],"type":"topic","role":"symbol","title":"CharcoalSize","fragments":[{"kind":"keyword","text":"struct"},{"kind":"text","text":" "},{"kind":"identifier","text":"CharcoalSize"}],"navigatorTitle":[{"kind":"identifier","text":"CharcoalSize"}]},"Spinners.png":{"identifier":"Spinners.png","variants":[{"traits":["2x","light"],"url":"\/images\/charcoal-ios.Charcoal\/Spinners@2x.png"},{"traits":["2x","dark"],"url":"\/images\/charcoal-ios.Charcoal\/Spinners~dark@2x.png"}],"type":"image","alt":"Charcoal spinners are designed to display a loading state."},"doc://charcoal-ios.Charcoal/documentation/Charcoal/CharcoalOverlayInteractionMode":{"fragments":[{"text":"enum","kind":"keyword"},{"kind":"text","text":" "},{"kind":"identifier","text":"CharcoalOverlayInteractionMode"}],"identifier":"doc:\/\/charcoal-ios.Charcoal\/documentation\/Charcoal\/CharcoalOverlayInteractionMode","title":"CharcoalOverlayInteractionMode","abstract":[],"url":"\/documentation\/charcoal\/charcoaloverlayinteractionmode","role":"symbol","type":"topic","navigatorTitle":[{"kind":"identifier","text":"CharcoalOverlayInteractionMode"}],"kind":"symbol"},"TextFields.png":{"variants":[{"traits":["2x","light"],"url":"\/images\/charcoal-ios.Charcoal\/TextFields@2x.png"},{"url":"\/images\/charcoal-ios.Charcoal\/TextFields~dark@2x.png","traits":["2x","dark"]}],"identifier":"TextFields.png","type":"image","alt":"Charcoal Textfields are designed to be used in a variety of contexts and are highly customizable."},"doc://charcoal-ios.Charcoal/documentation/Charcoal/CharcoalAsset":{"type":"topic","kind":"symbol","title":"CharcoalAsset","identifier":"doc:\/\/charcoal-ios.Charcoal\/documentation\/Charcoal\/CharcoalAsset","url":"\/documentation\/charcoal\/charcoalasset","abstract":[],"role":"symbol","navigatorTitle":[{"text":"CharcoalAsset","kind":"identifier"}],"fragments":[{"text":"enum","kind":"keyword"},{"text":" ","kind":"text"},{"kind":"identifier","text":"CharcoalAsset"}]},"doc://charcoal-ios.Charcoal/documentation/Charcoal/CharcoalTypography10":{"kind":"symbol","fragments":[{"text":"class","kind":"keyword"},{"kind":"text","text":" "},{"text":"CharcoalTypography10","kind":"identifier"}],"type":"topic","title":"CharcoalTypography10","abstract":[],"role":"symbol","navigatorTitle":[{"text":"CharcoalTypography10","kind":"identifier"}],"identifier":"doc:\/\/charcoal-ios.Charcoal\/documentation\/Charcoal\/CharcoalTypography10","url":"\/documentation\/charcoal\/charcoaltypography10"},"doc://charcoal-ios.Charcoal/documentation/Charcoal/CharcoalButton":{"fragments":[{"kind":"keyword","text":"protocol"},{"kind":"text","text":" "},{"kind":"identifier","text":"CharcoalButton"}],"navigatorTitle":[{"kind":"identifier","text":"CharcoalButton"}],"identifier":"doc:\/\/charcoal-ios.Charcoal\/documentation\/Charcoal\/CharcoalButton","title":"CharcoalButton","kind":"symbol","url":"\/documentation\/charcoal\/charcoalbutton","abstract":[],"type":"topic","role":"symbol"},"doc://charcoal-ios.Charcoal/documentation/Charcoal/DynamicType":{"images":[{"type":"icon","identifier":"charcoal-icon.png"}],"url":"\/documentation\/charcoal\/dynamictype","identifier":"doc:\/\/charcoal-ios.Charcoal\/documentation\/Charcoal\/DynamicType","kind":"article","type":"topic","title":"Charocal Dynamic Type","abstract":[{"text":"CharcoalはデフォルトでDynamic Typeをサポートしています。この機能を無効にしたい場合は、以下の手順をご参照ください。","type":"text"}],"role":"article"},"doc://charcoal-ios.Charcoal/documentation/Charcoal/CharcoalToast":{"kind":"symbol","url":"\/documentation\/charcoal\/charcoaltoast","fragments":[{"text":"class","kind":"keyword"},{"text":" ","kind":"text"},{"kind":"identifier","text":"CharcoalToast"}],"abstract":[],"type":"topic","title":"CharcoalToast","navigatorTitle":[{"text":"CharcoalToast","kind":"identifier"}],"identifier":"doc:\/\/charcoal-ios.Charcoal\/documentation\/Charcoal\/CharcoalToast","role":"symbol"},"doc://charcoal-ios.Charcoal/documentation/Charcoal/CharcoalBalloon":{"fragments":[{"text":"class","kind":"keyword"},{"kind":"text","text":" "},{"text":"CharcoalBalloon","kind":"identifier"}],"type":"topic","title":"CharcoalBalloon","role":"symbol","navigatorTitle":[{"kind":"identifier","text":"CharcoalBalloon"}],"url":"\/documentation\/charcoal\/charcoalballoon","identifier":"doc:\/\/charcoal-ios.Charcoal\/documentation\/Charcoal\/CharcoalBalloon","abstract":[],"kind":"symbol"},"doc://charcoal-ios.Charcoal/documentation/Charcoal/CharcoalButtonModifier":{"type":"topic","role":"symbol","fragments":[{"kind":"keyword","text":"protocol"},{"text":" ","kind":"text"},{"kind":"identifier","text":"CharcoalButtonModifier"}],"navigatorTitle":[{"text":"CharcoalButtonModifier","kind":"identifier"}],"url":"\/documentation\/charcoal\/charcoalbuttonmodifier","identifier":"doc:\/\/charcoal-ios.Charcoal\/documentation\/Charcoal\/CharcoalButtonModifier","abstract":[],"kind":"symbol","title":"CharcoalButtonModifier"},"doc://charcoal-ios.Charcoal/documentation/Charcoal/charcoalFoundation-swift.var":{"role":"symbol","title":"charcoalFoundation","identifier":"doc:\/\/charcoal-ios.Charcoal\/documentation\/Charcoal\/charcoalFoundation-swift.var","type":"topic","url":"\/documentation\/charcoal\/charcoalfoundation-swift.var","kind":"symbol","abstract":[],"fragments":[{"kind":"keyword","text":"let"},{"text":" ","kind":"text"},{"text":"charcoalFoundation","kind":"identifier"},{"text":": ","kind":"text"},{"text":"CharcoalFoundation","kind":"typeIdentifier","preciseIdentifier":"s:14CharcoalShared0A10FoundationV"}]},"doc://charcoal-ios.Charcoal/documentation/Charcoal":{"role":"collection","title":"Charcoal","images":[{"type":"icon","identifier":"charcoal-icon.png"}],"url":"\/documentation\/charcoal","type":"topic","identifier":"doc:\/\/charcoal-ios.Charcoal\/documentation\/Charcoal","kind":"symbol","abstract":[{"type":"text","text":"PIXIV Design System"}]},"doc://charcoal-ios.Charcoal/documentation/Charcoal/Switch":{"kind":"article","images":[{"type":"card","identifier":"Switch.png"}],"type":"topic","url":"\/documentation\/charcoal\/switch","abstract":[{"text":"Charcoal Switches are designed to allow the user to toggle between two states.","type":"text"}],"identifier":"doc:\/\/charcoal-ios.Charcoal\/documentation\/Charcoal\/Switch","title":"Charocal Switches","role":"collectionGroup"},"doc://charcoal-ios.Charcoal/documentation/Charcoal/CharcoalSnackBar":{"navigatorTitle":[{"kind":"identifier","text":"CharcoalSnackBar"}],"url":"\/documentation\/charcoal\/charcoalsnackbar","title":"CharcoalSnackBar","kind":"symbol","role":"symbol","identifier":"doc:\/\/charcoal-ios.Charcoal\/documentation\/Charcoal\/CharcoalSnackBar","abstract":[],"fragments":[{"text":"class","kind":"keyword"},{"kind":"text","text":" "},{"text":"CharcoalSnackBar","kind":"identifier"}],"type":"topic"},"doc://charcoal-ios.Charcoal/documentation/Charcoal/CharcoalBorderRadius":{"title":"CharcoalBorderRadius","abstract":[],"kind":"symbol","role":"symbol","navigatorTitle":[{"text":"CharcoalBorderRadius","kind":"identifier"}],"identifier":"doc:\/\/charcoal-ios.Charcoal\/documentation\/Charcoal\/CharcoalBorderRadius","type":"topic","url":"\/documentation\/charcoal\/charcoalborderradius","fragments":[{"text":"struct","kind":"keyword"},{"text":" ","kind":"text"},{"text":"CharcoalBorderRadius","kind":"identifier"}]},"doc://charcoal-ios.Charcoal/documentation/Charcoal/CharcoalLinkButton":{"type":"topic","abstract":[],"title":"CharcoalLinkButton","identifier":"doc:\/\/charcoal-ios.Charcoal\/documentation\/Charcoal\/CharcoalLinkButton","role":"symbol","url":"\/documentation\/charcoal\/charcoallinkbutton","navigatorTitle":[{"kind":"identifier","text":"CharcoalLinkButton"}],"fragments":[{"kind":"keyword","text":"class"},{"text":" ","kind":"text"},{"text":"CharcoalLinkButton","kind":"identifier"}],"kind":"symbol"},"doc://charcoal-ios.Charcoal/documentation/Charcoal/CharcoalConfig":{"identifier":"doc:\/\/charcoal-ios.Charcoal\/documentation\/Charcoal\/CharcoalConfig","kind":"symbol","title":"CharcoalConfig","url":"\/documentation\/charcoal\/charcoalconfig","role":"symbol","type":"topic","abstract":[],"fragments":[{"text":"struct","kind":"keyword"},{"text":" ","kind":"text"},{"kind":"identifier","text":"CharcoalConfig"}],"navigatorTitle":[{"text":"CharcoalConfig","kind":"identifier"}]},"doc://charcoal-ios.Charcoal/documentation/Charcoal/ColorAsset":{"identifier":"doc:\/\/charcoal-ios.Charcoal\/documentation\/Charcoal\/ColorAsset","type":"topic","fragments":[{"kind":"keyword","text":"class"},{"kind":"text","text":" "},{"kind":"identifier","text":"ColorAsset"}],"role":"symbol","navigatorTitle":[{"text":"ColorAsset","kind":"identifier"}],"title":"ColorAsset","url":"\/documentation\/charcoal\/colorasset","kind":"symbol","abstract":[]},"doc://charcoal-ios.Charcoal/documentation/Charcoal/CharcoalDefaultMButton":{"kind":"symbol","role":"symbol","url":"\/documentation\/charcoal\/charcoaldefaultmbutton","identifier":"doc:\/\/charcoal-ios.Charcoal\/documentation\/Charcoal\/CharcoalDefaultMButton","fragments":[{"kind":"keyword","text":"class"},{"text":" ","kind":"text"},{"text":"CharcoalDefaultMButton","kind":"identifier"}],"navigatorTitle":[{"kind":"identifier","text":"CharcoalDefaultMButton"}],"title":"CharcoalDefaultMButton","type":"topic","abstract":[]},"doc://charcoal-ios.Charcoal/documentation/Charcoal/Buttons":{"images":[{"type":"card","identifier":"Buttons.png"}],"url":"\/documentation\/charcoal\/buttons","identifier":"doc:\/\/charcoal-ios.Charcoal\/documentation\/Charcoal\/Buttons","kind":"article","type":"topic","title":"Charocal Buttons","abstract":[{"text":"Charcoal Buttons are designed to be used in a variety of contexts and are highly customizable.","type":"text"}],"role":"collectionGroup"},"Toasts.png":{"variants":[{"traits":["2x","light"],"url":"\/images\/charcoal-ios.Charcoal\/Toasts@2x.png"},{"traits":["2x","dark"],"url":"\/images\/charcoal-ios.Charcoal\/Toasts~dark@2x.png"}],"identifier":"Toasts.png","type":"image","alt":"Charcoal Toasts can be used to display a message and Snackbar to the user."},"doc://charcoal-ios.Charcoal/documentation/Charcoal/CharcoalThe12":{"navigatorTitle":[{"text":"CharcoalThe12","kind":"identifier"}],"kind":"symbol","fragments":[{"kind":"keyword","text":"struct"},{"text":" ","kind":"text"},{"kind":"identifier","text":"CharcoalThe12"}],"role":"symbol","type":"topic","abstract":[],"title":"CharcoalThe12","url":"\/documentation\/charcoal\/charcoalthe12","identifier":"doc:\/\/charcoal-ios.Charcoal\/documentation\/Charcoal\/CharcoalThe12"},"doc://charcoal-ios.Charcoal/documentation/Charcoal/CharcoalSpinner-swift.struct":{"fragments":[{"kind":"keyword","text":"struct"},{"text":" ","kind":"text"},{"text":"CharcoalSpinner","kind":"identifier"}],"kind":"symbol","url":"\/documentation\/charcoal\/charcoalspinner-swift.struct","title":"CharcoalSpinner","type":"topic","abstract":[],"identifier":"doc:\/\/charcoal-ios.Charcoal\/documentation\/Charcoal\/CharcoalSpinner-swift.struct","navigatorTitle":[{"kind":"identifier","text":"CharcoalSpinner"}],"role":"symbol"},"doc://charcoal-ios.Charcoal/documentation/Charcoal/CharcoalTypography20":{"title":"CharcoalTypography20","abstract":[],"url":"\/documentation\/charcoal\/charcoaltypography20","fragments":[{"kind":"keyword","text":"class"},{"text":" ","kind":"text"},{"text":"CharcoalTypography20","kind":"identifier"}],"navigatorTitle":[{"kind":"identifier","text":"CharcoalTypography20"}],"type":"topic","kind":"symbol","role":"symbol","identifier":"doc:\/\/charcoal-ios.Charcoal\/documentation\/Charcoal\/CharcoalTypography20"},"doc://charcoal-ios.Charcoal/documentation/Charcoal/CharcoalTypographyLabel":{"kind":"symbol","fragments":[{"text":"class","kind":"keyword"},{"text":" ","kind":"text"},{"text":"CharcoalTypographyLabel","kind":"identifier"}],"type":"topic","title":"CharcoalTypographyLabel","abstract":[],"role":"symbol","navigatorTitle":[{"kind":"identifier","text":"CharcoalTypographyLabel"}],"identifier":"doc:\/\/charcoal-ios.Charcoal\/documentation\/Charcoal\/CharcoalTypographyLabel","url":"\/documentation\/charcoal\/charcoaltypographylabel"},"doc://charcoal-ios.Charcoal/documentation/Charcoal/CharcoalFoundation-swift.struct":{"abstract":[],"kind":"symbol","title":"CharcoalFoundation","type":"topic","identifier":"doc:\/\/charcoal-ios.Charcoal\/documentation\/Charcoal\/CharcoalFoundation-swift.struct","url":"\/documentation\/charcoal\/charcoalfoundation-swift.struct","fragments":[{"text":"struct","kind":"keyword"},{"text":" ","kind":"text"},{"text":"CharcoalFoundation","kind":"identifier"}],"navigatorTitle":[{"kind":"identifier","text":"CharcoalFoundation"}],"role":"symbol"},"doc://charcoal-ios.Charcoal/documentation/Charcoal/Tooltips":{"images":[{"type":"card","identifier":"Tooltips.png"}],"url":"\/documentation\/charcoal\/tooltips","identifier":"doc:\/\/charcoal-ios.Charcoal\/documentation\/Charcoal\/Tooltips","kind":"article","type":"topic","title":"Charocal Tooltips","abstract":[{"text":"Charcoal Tooltips can be used to provide additional information about an element when the user click on it.","type":"text"}],"role":"collectionGroup"},"Buttons.png":{"variants":[{"traits":["2x","light"],"url":"\/images\/charcoal-ios.Charcoal\/Buttons@2x.png"},{"url":"\/images\/charcoal-ios.Charcoal\/Buttons~dark@2x.png","traits":["2x","dark"]}],"identifier":"Buttons.png","type":"image","alt":"Charcoal buttons are designed to be used in a variety of contexts and are highly customizable."},"doc://charcoal-ios.Charcoal/documentation/Charcoal/Typographies":{"images":[{"type":"card","identifier":"Typographies.png"}],"url":"\/documentation\/charcoal\/typographies","identifier":"doc:\/\/charcoal-ios.Charcoal\/documentation\/Charcoal\/Typographies","kind":"article","type":"topic","title":"Charocal Typographies","abstract":[{"text":"Charcoal Typographies are designed to be used in a variety of contexts and are highly customizable.","type":"text"}],"role":"collectionGroup"},"doc://charcoal-ios.Charcoal/documentation/Charcoal/CharcoalSpacing":{"identifier":"doc:\/\/charcoal-ios.Charcoal\/documentation\/Charcoal\/CharcoalSpacing","navigatorTitle":[{"text":"CharcoalSpacing","kind":"identifier"}],"type":"topic","abstract":[],"url":"\/documentation\/charcoal\/charcoalspacing","title":"CharcoalSpacing","fragments":[{"kind":"keyword","text":"struct"},{"kind":"text","text":" "},{"text":"CharcoalSpacing","kind":"identifier"}],"kind":"symbol","role":"symbol"},"doc://charcoal-ios.Charcoal/documentation/Charcoal/Balloons":{"kind":"article","images":[{"type":"card","identifier":"Balloon.png"}],"type":"topic","url":"\/documentation\/charcoal\/balloons","abstract":[{"text":"Charcoal Balloons are designed to show a message in a balloon-shaped container.","type":"text"}],"identifier":"doc:\/\/charcoal-ios.Charcoal\/documentation\/Charcoal\/Balloons","title":"Charocal Balloons","role":"collectionGroup"},"doc://charcoal-ios.Charcoal/documentation/Charcoal/CharcoalSwitchingButton":{"title":"CharcoalSwitchingButton","identifier":"doc:\/\/charcoal-ios.Charcoal\/documentation\/Charcoal\/CharcoalSwitchingButton","kind":"symbol","url":"\/documentation\/charcoal\/charcoalswitchingbutton","role":"symbol","type":"topic","abstract":[],"fragments":[{"text":"class","kind":"keyword"},{"kind":"text","text":" "},{"text":"CharcoalSwitchingButton","kind":"identifier"}],"navigatorTitle":[{"kind":"identifier","text":"CharcoalSwitchingButton"}]},"doc://charcoal-ios.Charcoal/documentation/Charcoal/CharcoalButtonStyle":{"url":"\/documentation\/charcoal\/charcoalbuttonstyle","role":"symbol","identifier":"doc:\/\/charcoal-ios.Charcoal\/documentation\/Charcoal\/CharcoalButtonStyle","fragments":[{"text":"enum","kind":"keyword"},{"text":" ","kind":"text"},{"text":"CharcoalButtonStyle","kind":"identifier"}],"title":"CharcoalButtonStyle","abstract":[],"type":"topic","kind":"symbol","navigatorTitle":[{"text":"CharcoalButtonStyle","kind":"identifier"}]},"doc://charcoal-ios.Charcoal/documentation/Charcoal/CharcoalToastAnimationConfiguration":{"kind":"symbol","identifier":"doc:\/\/charcoal-ios.Charcoal\/documentation\/Charcoal\/CharcoalToastAnimationConfiguration","fragments":[{"text":"struct","kind":"keyword"},{"text":" ","kind":"text"},{"text":"CharcoalToastAnimationConfiguration","kind":"identifier"}],"title":"CharcoalToastAnimationConfiguration","url":"\/documentation\/charcoal\/charcoaltoastanimationconfiguration","abstract":[],"type":"topic","role":"symbol","navigatorTitle":[{"text":"CharcoalToastAnimationConfiguration","kind":"identifier"}]},"doc://charcoal-ios.Charcoal/documentation/Charcoal/CharcoalPrimarySButton":{"type":"topic","abstract":[],"title":"CharcoalPrimarySButton","identifier":"doc:\/\/charcoal-ios.Charcoal\/documentation\/Charcoal\/CharcoalPrimarySButton","role":"symbol","url":"\/documentation\/charcoal\/charcoalprimarysbutton","navigatorTitle":[{"kind":"identifier","text":"CharcoalPrimarySButton"}],"fragments":[{"text":"class","kind":"keyword"},{"text":" ","kind":"text"},{"kind":"identifier","text":"CharcoalPrimarySButton"}],"kind":"symbol"}}}